pytest_tornasync/__init__.py
pytest_tornasync/plugin.py
pytest_tornasync-0.6.0.post2.data/data/LICENSE
pytest_tornasync-0.6.0.post2.dist-info/LICENSE
pytest_tornasync-0.6.0.post2.dist-info/METADATA
pytest_tornasync-0.6.0.post2.dist-info/WHEEL
pytest_tornasync-0.6.0.post2.dist-info/entry_points.txt
pytest_tornasync-0.6.0.post2.dist-info/top_level.txt
pytest_tornasync-0.6.0.post2.dist-info/RECORD
