Metadata-Version: 1.1
Name: pytest-tornasync
Version: 0.6.0.post2
Summary: py.test plugin for testing Python 3.5+ Tornado code
Home-page: https://github.com/eukaryote/pytest-tornasync
Author: Calvin Smith
Author-email: sapientdust+pytest-tornasync@gmail.com
License: http://www.opensource.org/licenses/mit-license.php
Keywords: testing py.test tornado
Platform: any
Classifier: Programming Language :: Python :: 3 :: Only
Classifier: License :: OSI Approved :: MIT License
Classifier: Environment :: Console
Classifier: Development Status :: 3 - Alpha
Classifier: Intended Audience :: Developers
Classifier: Framework :: Pytest
Classifier: Topic :: Software Development :: Testing
Classifier: Programming Language :: Python :: 3
Classifier: Programming Language :: Python :: 3.5
Classifier: Programming Language :: Python :: 3.6
Classifier: Programming Language :: Python :: 3.7
